pyv6m/__init__.py
pyv6m/pyv6m.py
pyv6m/test.py
pyv6m/v6m.py
pyv6m/v6mrelay.py
pyv6m/v6msensor.py
pyvm6-0.0.1.dist-info/LICENSE
pyvm6-0.0.1.dist-info/METADATA
pyvm6-0.0.1.dist-info/WHEEL
pyvm6-0.0.1.dist-info/top_level.txt
pyvm6-0.0.1.dist-info/RECORD
