Metadata-Version: 2.1
Name: pyvm6
Version: 0.0.1
Summary: VM6 relay controller over Ethernet
Home-page: https://github.com/dubnom/pyvm6
Author: Michael Dubno
Author-email: michael@dubno.com
License: UNKNOWN
Platform: UNKNOWN
Classifier: Programming Language :: Python :: 3
Classifier: License :: OSI Approved :: MIT License
Classifier: Operating System :: OS Independent
